CyScenario.h
CyWrappers.cpp
CyWrappers.h
MANIFEST.in
PyDeepCL.cxx
README.rst
setup.py
test_deepcl.py
test_lowlevel.py
version.txt
DeepCL.egg-info/PKG-INFO
DeepCL.egg-info/SOURCES.txt
DeepCL.egg-info/dependency_links.txt
DeepCL.egg-info/top_level.txt
test/test_basic.py
test/test_seed.py