Metadata-Version: 1.1
Name: DeepCL
Version: 8.5.2
Summary: python wrapper for DeepCL deep convolutional neural network library for OpenCL
Home-page: https://github.com/hughperkins/DeepCL
Author: Hugh Perkins
Author-email: hughperkins@gmail.com
License: MPL
Platform: UNKNOWN
Classifier: Development Status :: 5 - Production/Stable
Classifier: Topic :: Scientific/Engineering :: Artificial Intelligence
Classifier: License :: OSI Approved :: Mozilla Public License 2.0 (MPL 2.0)
